<?xml version='1.0' encoding='UTF-8'?>
<types:mule xmlns:types="http://www.mulesoft.org/schema/mule/types">
  <types:catalog>
    <types:type name="auto_1fa58d6b-e1f9-459d-8be5-191d53082e37_Input-Payload" format="java">
      <types:shape format="weave" example="weave/autogenerated/1fa58d6b-e1f9-459d-8be5-191d53082e37/Input-Payload.wev" autogeneratedOrigin="930c2728-14e7-4dc5-8c7c-2babc45f6ade"><![CDATA[%dw 2.0

type auto_1fa58d6b_e1f9_459d_8be5_191d53082e37_Input_Payload = Any

]]></types:shape>
    </types:type>
    <types:type name="auto_1fa58d6b-e1f9-459d-8be5-191d53082e37_Input-Attributes" format="java">
      <types:shape format="weave" example="weave/autogenerated/1fa58d6b-e1f9-459d-8be5-191d53082e37/Input-Attributes.wev" autogeneratedOrigin="930c2728-14e7-4dc5-8c7c-2babc45f6ade"><![CDATA[%dw 2.0

type auto_1fa58d6b_e1f9_459d_8be5_191d53082e37_Input_Attributes = {|
  listenerPath: String, 
  rawRequestPath: String, 
  relativePath: String, 
  maskedRequestPath: String, 
  version: String, 
  scheme: String, 
  method: String, 
  requestUri: String, 
  rawRequestUri: String, 
  queryString: String, 
  localAddress: String, 
  remoteAddress: String, 
  clientCertificate?: java_security_cert_Certificate, 
  queryParams: { _?: String }, 
  uriParams: { _?: String }, 
  requestPath: String, 
  headers: { _?: String }
|} {"typeAlias": "HttpRequestAttributes",
"typeId": "org.mule.extension.http.api.HttpRequestAttributes"}
type java_security_cert_Certificate = {|
  encoded?: Binary, 
  publicKey?: java_security_PublicKey, 
  "type"?: String
|} {"typeAlias": "Certificate",
"typeId": "java.security.cert.Certificate"}
type java_security_PublicKey = {|  |} {"typeAlias": "PublicKey",
"typeId": "java.security.PublicKey"}





]]></types:shape>
    </types:type>
    <types:type name="auto_1fa58d6b-e1f9-459d-8be5-191d53082e37_Output-Payload" format="java">
      <types:shape format="weave" example="weave/autogenerated/1fa58d6b-e1f9-459d-8be5-191d53082e37/Output-Payload.wev" autogeneratedOrigin="930c2728-14e7-4dc5-8c7c-2babc45f6ade"><![CDATA[%dw 2.0

type auto_1fa58d6b_e1f9_459d_8be5_191d53082e37_Output_Payload = Any

]]></types:shape>
    </types:type>
    <types:type name="auto_1fa58d6b-e1f9-459d-8be5-191d53082e37_Output-Attributes" format="java">
      <types:shape format="weave" example="weave/autogenerated/1fa58d6b-e1f9-459d-8be5-191d53082e37/Output-Attributes.wev" autogeneratedOrigin="930c2728-14e7-4dc5-8c7c-2babc45f6ade"><![CDATA[%dw 2.0

type auto_1fa58d6b_e1f9_459d_8be5_191d53082e37_Output_Attributes = {|
  listenerPath: String, 
  rawRequestPath: String, 
  relativePath: String, 
  maskedRequestPath: String, 
  version: String, 
  scheme: String, 
  method: String, 
  requestUri: String, 
  rawRequestUri: String, 
  queryString: String, 
  localAddress: String, 
  remoteAddress: String, 
  clientCertificate?: java_security_cert_Certificate, 
  queryParams: { _?: String }, 
  uriParams: { _?: String }, 
  requestPath: String, 
  headers: { _?: String }
|} {"typeAlias": "HttpRequestAttributes",
"typeId": "org.mule.extension.http.api.HttpRequestAttributes"}
type java_security_cert_Certificate = {|
  encoded?: Binary, 
  publicKey?: java_security_PublicKey, 
  "type"?: String
|} {"typeAlias": "Certificate",
"typeId": "java.security.cert.Certificate"}
type java_security_PublicKey = {|  |} {"typeAlias": "PublicKey",
"typeId": "java.security.PublicKey"}





]]></types:shape>
    </types:type>
    <types:type name="auto_1fa58d6b-e1f9-459d-8be5-191d53082e37_Output-Variables-insertResult" format="java">
      <types:shape format="weave" example="weave/autogenerated/1fa58d6b-e1f9-459d-8be5-191d53082e37/Output-Variables-insertResult.wev" autogeneratedOrigin="930c2728-14e7-4dc5-8c7c-2babc45f6ade"><![CDATA[%dw 2.0

type auto_1fa58d6b_e1f9_459d_8be5_191d53082e37_Output_Variables_insertResult = {|
  affectedRows?: Number, 
  generatedKeys?: { _?: Number }
|} {"typeAlias": "StatementResult",
"typeId": "org.mule.extension.db.api.StatementResult"}

]]></types:shape>
    </types:type>
    <types:type name="auto_ce02b036-917b-4348-af7e-bcf4da1599ba_Input-Payload" format="java">
      <types:shape format="weave" example="weave/autogenerated/ce02b036-917b-4348-af7e-bcf4da1599ba/Input-Payload.wev" autogeneratedOrigin="01438966-a5f1-49fb-a0d9-f49e16cc1b01"><![CDATA[%dw 2.0

type auto_ce02b036_917b_4348_af7e_bcf4da1599ba_Input_Payload = Any

]]></types:shape>
    </types:type>
    <types:type name="auto_ce02b036-917b-4348-af7e-bcf4da1599ba_Input-Attributes" format="java">
      <types:shape format="weave" example="weave/autogenerated/ce02b036-917b-4348-af7e-bcf4da1599ba/Input-Attributes.wev" autogeneratedOrigin="01438966-a5f1-49fb-a0d9-f49e16cc1b01"><![CDATA[%dw 2.0

type auto_ce02b036_917b_4348_af7e_bcf4da1599ba_Input_Attributes = {|
  listenerPath: String, 
  rawRequestPath: String, 
  relativePath: String, 
  maskedRequestPath: String, 
  version: String, 
  scheme: String, 
  method: String, 
  requestUri: String, 
  rawRequestUri: String, 
  queryString: String, 
  localAddress: String, 
  remoteAddress: String, 
  clientCertificate?: java_security_cert_Certificate, 
  queryParams: { _?: String }, 
  uriParams: { _?: String }, 
  requestPath: String, 
  headers: { _?: String }
|} {"typeAlias": "HttpRequestAttributes",
"typeId": "org.mule.extension.http.api.HttpRequestAttributes"}
type java_security_cert_Certificate = {|
  encoded?: Binary, 
  publicKey?: java_security_PublicKey, 
  "type"?: String
|} {"typeAlias": "Certificate",
"typeId": "java.security.cert.Certificate"}
type java_security_PublicKey = {|  |} {"typeAlias": "PublicKey",
"typeId": "java.security.PublicKey"}





]]></types:shape>
    </types:type>
    <types:type name="auto_ce02b036-917b-4348-af7e-bcf4da1599ba_Input-Variables-patientId" format="java">
      <types:shape format="weave" example="weave/autogenerated/ce02b036-917b-4348-af7e-bcf4da1599ba/Input-Variables-patientId.wev" autogeneratedOrigin="01438966-a5f1-49fb-a0d9-f49e16cc1b01"><![CDATA[%dw 2.0

type auto_ce02b036_917b_4348_af7e_bcf4da1599ba_Input_Variables_patientId = String | Null

]]></types:shape>
    </types:type>
    <types:type name="auto_ce02b036-917b-4348-af7e-bcf4da1599ba_Output-Payload" format="java">
      <types:shape format="weave" example="weave/autogenerated/ce02b036-917b-4348-af7e-bcf4da1599ba/Output-Payload.wev" autogeneratedOrigin="01438966-a5f1-49fb-a0d9-f49e16cc1b01"><![CDATA[%dw 2.0

type auto_ce02b036_917b_4348_af7e_bcf4da1599ba_Output_Payload = Array<{ _?: java_lang_Object }>
type java_lang_Object = {|  |} {"typeAlias": "Object",
"class": "java.lang.Object",
"typeId": "java.lang.Object"}



]]></types:shape>
    </types:type>
    <types:type name="auto_ce02b036-917b-4348-af7e-bcf4da1599ba_Output-Attributes" format="java">
      <types:shape format="weave" example="weave/autogenerated/ce02b036-917b-4348-af7e-bcf4da1599ba/Output-Attributes.wev" autogeneratedOrigin="01438966-a5f1-49fb-a0d9-f49e16cc1b01"><![CDATA[%dw 2.0

type auto_ce02b036_917b_4348_af7e_bcf4da1599ba_Output_Attributes = Null

]]></types:shape>
    </types:type>
    <types:type name="auto_ce02b036-917b-4348-af7e-bcf4da1599ba_Output-Variables-patientId" format="java">
      <types:shape format="weave" example="weave/autogenerated/ce02b036-917b-4348-af7e-bcf4da1599ba/Output-Variables-patientId.wev" autogeneratedOrigin="01438966-a5f1-49fb-a0d9-f49e16cc1b01"><![CDATA[%dw 2.0

type auto_ce02b036_917b_4348_af7e_bcf4da1599ba_Output_Variables_patientId = String | Null

]]></types:shape>
    </types:type>
  </types:catalog>
  <types:enrichment select="#1fa58d6b-e1f9-459d-8be5-191d53082e37">
    <types:processor-declaration>
      <types:input-event>
        <types:message>
          <types:payload type="auto_1fa58d6b-e1f9-459d-8be5-191d53082e37_Input-Payload"/>
          <types:attributes type="auto_1fa58d6b-e1f9-459d-8be5-191d53082e37_Input-Attributes"/>
        </types:message>
      </types:input-event>
      <types:output-event>
        <types:message>
          <types:payload type="auto_1fa58d6b-e1f9-459d-8be5-191d53082e37_Output-Payload"/>
          <types:attributes type="auto_1fa58d6b-e1f9-459d-8be5-191d53082e37_Output-Attributes"/>
        </types:message>
        <types:variables>
          <types:variable name="insertResult" type="auto_1fa58d6b-e1f9-459d-8be5-191d53082e37_Output-Variables-insertResult"/>
        </types:variables>
      </types:output-event>
    </types:processor-declaration>
  </types:enrichment>
  <types:enrichment select="#ce02b036-917b-4348-af7e-bcf4da1599ba">
    <types:processor-declaration>
      <types:input-event>
        <types:message>
          <types:payload type="auto_ce02b036-917b-4348-af7e-bcf4da1599ba_Input-Payload"/>
          <types:attributes type="auto_ce02b036-917b-4348-af7e-bcf4da1599ba_Input-Attributes"/>
        </types:message>
        <types:variables>
          <types:variable name="patientId" type="auto_ce02b036-917b-4348-af7e-bcf4da1599ba_Input-Variables-patientId"/>
        </types:variables>
      </types:input-event>
      <types:output-event>
        <types:message>
          <types:payload type="auto_ce02b036-917b-4348-af7e-bcf4da1599ba_Output-Payload"/>
          <types:attributes type="auto_ce02b036-917b-4348-af7e-bcf4da1599ba_Output-Attributes"/>
        </types:message>
        <types:variables>
          <types:variable name="patientId" type="auto_ce02b036-917b-4348-af7e-bcf4da1599ba_Output-Variables-patientId"/>
        </types:variables>
      </types:output-event>
    </types:processor-declaration>
  </types:enrichment>
</types:mule>